market_graphs/__init__.py
market_graphs/admin.py
market_graphs/apps.py
market_graphs/models.py
market_graphs/tests.py
market_graphs/urls.py
market_graphs/views.py
market_graphs/migrations/__init__.py
market_graphs/templates/market_graphs/market_graphs.html
market_graphs/templates/market_graphs/test.html
market_graphs/templatetags/__init__.py
market_graphs/templatetags/market_graphs_custom_tags.py
mytester/__init__.py
mytester/asgi.py
mytester/settings.py
mytester/urls.py
mytester/wsgi.py
django_market_graphs-0.0.3.dist-info/LICENSE
django_market_graphs-0.0.3.dist-info/METADATA
django_market_graphs-0.0.3.dist-info/WHEEL
django_market_graphs-0.0.3.dist-info/top_level.txt
django_market_graphs-0.0.3.dist-info/RECORD
